wtrobot/__init__.py
wtrobot/cli/__init__.py
wtrobot/cli/main.py
wtrobot/cli/commands/__init__.py
wtrobot/cli/commands/clean.py
wtrobot/cli/commands/config.py
wtrobot/cli/commands/grid.py
wtrobot/cli/commands/run.py
wtrobot/utils/__init__.py
wtrobot/utils/logger.py
wtrobot/utils/util.py
wtrobot/wt_lib/__init__.py
wtrobot/wt_lib/actions/__init__.py
wtrobot/wt_lib/actions/action.py
wtrobot/wt_lib/brower_init/__init__.py
wtrobot/wt_lib/brower_init/browser_init.py
wtrobot/wt_lib/brower_init/browser_options.py
wtrobot/wt_lib/brower_init/grid_init.py
wtrobot/wt_lib/brower_init/main.py
wtrobot/wt_lib/operations/__init__.py
wtrobot/wt_lib/operations/operations.py
wtrobot/wt_lib/scripts/__init__.py
wtrobot/wt_lib/scripts/grid.py
wtrobot/wt_lib/testfile_parser/__init__.py
wtrobot/wt_lib/testfile_parser/old_testscript_parser.py
wtrobot/wt_lib/testfile_parser/parser.py
wtrobot/wt_lib/testfile_parser/testcase_parser.py
wtrobot/wt_lib/testfile_parser/testscript_parser.py
wtrobot-0.0.3.dist-info/LICENSE
wtrobot-0.0.3.dist-info/METADATA
wtrobot-0.0.3.dist-info/WHEEL
wtrobot-0.0.3.dist-info/entry_points.txt
wtrobot-0.0.3.dist-info/top_level.txt
wtrobot-0.0.3.dist-info/RECORD
