Metadata-Version: 2.1
Name: wtrobot
Version: 0.0.3
Summary: WTRobot is keyword driven web testing framework
Home-page: https://github.com/wtrobot/wtrobot
Author: Vishal Vijayraghavan
Author-email: vishalvvr@fedoraproject.org
License: MIT
Classifier: Operating System :: OS Independent
Classifier: Programming Language :: Python :: 3
Classifier: License :: OSI Approved :: MIT License
License-File: LICENSE
Requires-Dist: click ==8.1.3
Requires-Dist: pyyaml
Requires-Dist: requests
Requires-Dist: selenium ==4.6.1
Requires-Dist: webdriver-manager ==3.8.5
